emonoda/plugins/confetti/hass/__init__.py
emonoda/plugins/confetti/hass/templates/hass.emupdate.mako
emonoda_plugin_confetti_hass-1.0.1.dist-info/METADATA
emonoda_plugin_confetti_hass-1.0.1.dist-info/WHEEL
emonoda_plugin_confetti_hass-1.0.1.dist-info/top_level.txt
emonoda_plugin_confetti_hass-1.0.1.dist-info/RECORD
