Metadata-Version: 2.1
Name: emonoda-plugin-confetti-hass
Version: 1.0.1
Summary: Home Assistant confetti plugin for emonoda
Home-page: https://github.com/ASMfreaK/emonoda-plugin-confetti-hass
Author: Pletenev Pavel
Author-email: cpp.create@gmail.com
License: GPLv3
Platform: any
Classifier: License :: OSI Approved :: GNU General Public License v3 or later (GPLv3+)
Classifier: Programming Language :: Python :: 3.10
Classifier: Topic :: Software Development :: Libraries :: Python Modules
Classifier: Topic :: Communications :: File Sharing
Classifier: Topic :: Internet :: WWW/HTTP
Classifier: Topic :: Utilities
Classifier: Operating System :: OS Independent
Classifier: Intended Audience :: System Administrators
Classifier: Intended Audience :: End Users/Desktop
Requires-Dist: emonoda
Requires-Dist: homeassistant-api ==4.2.2
